pwclip/__init__.py
pwclip/__main__.py
pwclip/__pkginfo__.py
pwclip/cmdline.py
pwclip/passcrypt.py
pwclip/docs/pwclip.1
pwclip/example/ca.crt
pwclip/example/commands.rst
pwclip/example/passwords.yaml
pwclip/example/ssl.crt
pwclip/example/ssl.key
pwclip/lib/__init__.py
pwclip/lib/colortext/__init__.py
pwclip/lib/colortext/colortext.py
pwclip/lib/colortext/logger.py
pwclip/lib/executor/__init__.py
pwclip/lib/executor/executor.py
pwclip/lib/secrecy/__init__.py
pwclip/lib/secrecy/gpgtools.py
pwclip/lib/secrecy/yubi.py
pwclip/lib/system/__init__.py
pwclip/lib/system/android.py
pwclip/lib/system/clips.py
pwclip/lib/system/dictreplace.py
pwclip/lib/system/envconf.py
pwclip/lib/system/path.py
pwclip/lib/system/random.py
pwclip/lib/system/which.py
pwclip/lib/system/user/__init__.py
pwclip/lib/system/user/find.py
pwclip/lib/system/user/whoami.py
pwclip/lib/system/xlib/__init__.py
pwclip/lib/system/xlib/xinput.py
pwclip/lib/system/xlib/xkbid.py
pwclip/lib/system/xlib/xnotify.py
pwclip-1.7.16.data/data/share/man/man1/pwclip.1
pwclip-1.7.16.data/data/share/pwclip/ca.crt
pwclip-1.7.16.data/data/share/pwclip/commands.rst
pwclip-1.7.16.data/data/share/pwclip/passwords.yaml
pwclip-1.7.16.data/data/share/pwclip/ssl.crt
pwclip-1.7.16.data/data/share/pwclip/ssl.key
pwclip-1.7.16.dist-info/METADATA
pwclip-1.7.16.dist-info/WHEEL
pwclip-1.7.16.dist-info/entry_points.txt
pwclip-1.7.16.dist-info/top_level.txt
pwclip-1.7.16.dist-info/RECORD
