Metadata-Version: 2.1
Name: pwclip
Version: 1.7.16
Summary: password-manager - temporarily saves passwords to the clipboard
Home-page: https://github.com/d0n/pwclip
Author: Leon Pelzer
Author-email: mail@leonpelzer.de
License: GPLv3+
Download-URL: http://deb.janeiskla.de/ubuntu/pool/main/p/pwclip/python3-pwclip_1.7.16-1_all.deb
Platform: UNKNOWN
Classifier: Environment :: Console
Classifier: Environment :: MacOS X
Classifier: Environment :: Win32 (MS Windows)
Classifier: Environment :: X11 Applications
Classifier: Intended Audience :: Developers
Classifier: Intended Audience :: End Users/Desktop
Classifier: Intended Audience :: System Administrators
Classifier: Intended Audience :: Information Technology
Classifier: License :: OSI Approved :: GNU General Public License v3 or later (GPLv3+)
Classifier: Operating System :: OS Independent
Classifier: Programming Language :: Python :: 3
Classifier: Topic :: Security
Classifier: Topic :: Security :: Cryptography
Classifier: Topic :: Desktop Environment
Classifier: Topic :: Utilities
Classifier: Topic :: Desktop Environment
Provides: pwcli
Provides: pwclip
Provides: ykclip
Requires-Dist: PyYAML
Requires-Dist: argcomplete
Requires-Dist: psutil
Requires-Dist: py-notifier
Requires-Dist: pywin32 (>=1.0) ; platform_system == "Windows"
Requires-Dist: win10toast (>=0.9) ; platform_system == "Windows"
